Workbook
Name investimento_mensal: 'Fast Cash Investment -FAI'!$D$9:$D$9
Name patrimonio_acumulado: 'Fast Cash Investment -FAI'!$D$12:$D$12
Name qtd_anos: 'Fast Cash Investment -FAI'!$D$10:$D$10
Name rendimento_carteira: 'Fast Cash Investment -FAI'!$D$5:$D$5
Name rendimento_mensal: 'Fast Cash Investment -FAI'!$D$11:$D$11
Name salario_: 'Fast Cash Investment -FAI'!$D$4:$D$4
Name sugestao_investimento: 'Fast Cash Investment -FAI'!$D$6:$D$6

Sheet Fast Cash Investment -FAI
B1: Fast Cash Investiment
B3: Configurações
B4: Salário | D4: 1500
B5: Rendimento da Carteira | D5: 0.01
B6: Sugestão de Investimento (30%) | D6: =D4*30% -> 450
B8: Investimento Mensal
B9: Quanto Investir por Mês ? | D9: 300
B10: Por quantos Anos? | D10: 5
B11: Taxa de Rendimento Mensal | D11: 0.008
B12: Patrimônio Acumulado | D12: =FV(D11,D10*12,D9*-1) -> 22987.16
B13: Dividendos Mensais | D13: =D12*$D$5 -> 229.8716
B15: Cenários | D15: Dividendo
A16: 2 | B16: Quanto em 2 anos ? | C16: =FV($D$11,$A16*12,$D$9*-1 ) -> 7902.9465 | D16: =C16*$D$5 -> 79.029465
A17: 5 | B17: Quanto em 5 anos ? | C17: =FV($D$11,$A17*12,$D$9*-1 ) -> 22987.16 | D17: =C17*$D$5 -> 229.8716
A18: 10 | B18: Quanto em 10 anos ? | C18: =FV($D$11,$A18*12,$D$9*-1 ) -> 60065.241 | D18: =C18*$D$5 -> 600.65241
A19: 15 | B19: Quanto em 15 anos ? | C19: =FV($D$11,$A19*12,$D$9*-1 ) -> 119871.85 | D19: =C19*$D$5 -> 1198.7185
A20: 20 | B20: Quanto em 20 anos ? | C20: =FV($D$11,$A20*12,$D$9*-1 ) -> 216339.37 | D20: =C20*$D$5 -> 2163.3937
A21: 30 | B21: Quanto em 30 anos ? | C21: =FV($D$11,$A21*12,$D$9*-1 ) -> 622923.97 | D21: =C21*$D$5 -> 6229.2397
B24: PERFIL | D24: Agressivo
B25: VALOR A SER INVESTIDO POR MÊS | D25: =$D$9 -> 300
B27: TIPO DE FII | C27: Percentual Sugerido | D27: Valores
B28: TIJOLO | C28: =VLOOKUP($D$24&"-"&$B28,'Base para Fórmula'!$A:$D,4,FALSE) -> 0.2 | D28: =$D$25*C28 -> 60
B29: PAPEL | C29: =VLOOKUP($D$24&"-"&$B29,'Base para Fórmula'!$A:$D,4,FALSE) -> 0.2 | D29: =$D$25*C29 -> 60
B30: HÍBRIDO | C30: =VLOOKUP($D$24&"-"&$B30,'Base para Fórmula'!$A:$D,4,FALSE) -> 0.2 | D30: =$D$25*C30 -> 60
B31: FOFs | C31: =VLOOKUP($D$24&"-"&$B31,'Base para Fórmula'!$A:$D,4,FALSE) -> 0.15 | D31: =$D$25*C31 -> 45
B32: DESENVOLVIMENTO | C32: =VLOOKUP($D$24&"-"&$B32,'Base para Fórmula'!$A:$D,4,FALSE) -> 0.1 | D32: =$D$25*C32 -> 30
B33: HOTELARIAS | C33: =VLOOKUP($D$24&"-"&$B33,'Base para Fórmula'!$A:$D,4,FALSE) -> 0.15 | D33: =$D$25*C33 -> 45
B34: TOTAL | D34: =SUM($D$28:$D$33) -> 300

Sheet Base para Fórmula
A1: Base de Apoio
A3: Chave | B3: Perfil | C3: FII | D3: %
A4: =B4&"-"&C4 -> Conservador-TIJOLO | B4: Conservador | C4: TIJOLO | D4: 0.35
A5: =B5&"-"&C5 -> Conservador-PAPEL | B5: Conservador | C5: PAPEL | D5: 0.3
A6: =B6&"-"&C6 -> Conservador-HÍBRIDO | B6: Conservador | C6: HÍBRIDO | D6: 0.1
A7: =B7&"-"&C7 -> Conservador-FOFs | B7: Conservador | C7: FOFs | D7: 0.1
A8: =B8&"-"&C8 -> Conservador-DESENVOLVIMENTO | B8: Conservador | C8: DESENVOLVIMENTO | D8: 0.05
A9: =B9&"-"&C9 -> Conservador-HOTELARIAS | B9: Conservador | C9: HOTELARIAS | D9: 0.1
A10: =B10&"-"&C10 -> Moderado-TIJOLO | B10: Moderado | C10: TIJOLO | D10: 0.3
A11: =B11&"-"&C11 -> Moderado-PAPEL | B11: Moderado | C11: PAPEL | D11: 0.25
A12: =B12&"-"&C12 -> Moderado-HÍBRIDO | B12: Moderado | C12: HÍBRIDO | D12: 0.15
A13: =B13&"-"&C13 -> Moderado-FOFs | B13: Moderado | C13: FOFs | D13: 0.15
A14: =B14&"-"&C14 -> Moderado-DESENVOLVIMENTO | B14: Moderado | C14: DESENVOLVIMENTO | D14: 0.05
A15: =B15&"-"&C15 -> Moderado-HOTELARIAS | B15: Moderado | C15: HOTELARIAS | D15: 0.1
... A21: =B21&"-"&C21 -> Agressivo-HOTELARIAS | B21: Agressivo | C21: HOTELARIAS | D21: 0.15
